deeprehab_movements/__init__.py
deeprehab_movements/deeprehab_movements.py
deeprehab_movements/test_movements.py
deeprehab_movements-0.1.0.dist-info/METADATA
deeprehab_movements-0.1.0.dist-info/WHEEL
deeprehab_movements-0.1.0.dist-info/top_level.txt
deeprehab_movements-0.1.0.dist-info/RECORD
